[{"chord": "N", "start": 0, "end": 500}, {"chord": "F:maj", "start": 500, "end": 2300}, {"chord": "C:maj", "start": 2300, "end": 3800}, {"chord": "A#:maj", "start": 3800, "end": 5400}, {"chord": "F:maj", "start": 5400, "end": 7000}, {"chord": "A#:maj", "start": 7000, "end": 8600}, {"chord": "F:maj", "start": 8600, "end": 10300}, {"chord": "G:min", "start": 10300, "end": 12000}, {"chord": "C:maj", "start": 12000, "end": 13300}, {"chord": "F:maj", "start": 13300, "end": 16600}, {"chord": "A#:maj", "start": 16600, "end": 18200}, {"chord": "F:maj", "start": 18200, "end": 19700}, {"chord": "G:min", "start": 19700, "end": 21200}, {"chord": "C:maj", "start": 21200, "end": 22800}, {"chord": "F:maj", "start": 22800, "end": 30800}, {"chord": "C:maj", "start": 30800, "end": 32400}, {"chord": "A#:maj", "start": 32400, "end": 33800}, {"chord": "F:maj", "start": 33800, "end": 35400}, {"chord": "A#:maj", "start": 35400, "end": 37100}, {"chord": "F:maj", "start": 37100, "end": 38800}, {"chord": "G:min", "start": 38800, "end": 40000}, {"chord": "C:maj", "start": 40000, "end": 41700}, {"chord": "F:maj", "start": 41700, "end": 43400}, {"chord": "C:maj", "start": 43400, "end": 44900}, {"chord": "A#:maj", "start": 44900, "end": 46400}, {"chord": "F:maj", "start": 46400, "end": 48100}, {"chord": "A#:maj", "start": 48100, "end": 49800}, {"chord": "F:maj", "start": 49800, "end": 51400}, {"chord": "G:min", "start": 51400, "end": 52000}, {"chord": "C:maj", "start": 52000, "end": 52900}, {"chord": "F:maj", "start": 52900, "end": 56100}, {"chord": "C:maj", "start": 56100, "end": 57600}, {"chord": "C:min", "start": 57600, "end": 58300}, {"chord": "F:maj", "start": 58300, "end": 59200}, {"chord": "A#:maj", "start": 59200, "end": 60600}, {"chord": "F:maj", "start": 60600, "end": 62400}, {"chord": "G:min", "start": 62400, "end": 65200}, {"chord": "C:maj", "start": 65200, "end": 68800}, {"chord": "A:min", "start": 68800, "end": 70200}, {"chord": "D:maj", "start": 70200, "end": 71700}, {"chord": "A#:maj", "start": 71700, "end": 73200}, {"chord": "F:maj", "start": 73200, "end": 75000}, {"chord": "A#:maj", "start": 75000, "end": 76300}, {"chord": "F:maj", "start": 76300, "end": 78200}, {"chord": "A#:maj", "start": 78200, "end": 79600}, {"chord": "F:maj", "start": 79600, "end": 81400}, {"chord": "A#:maj", "start": 81400, "end": 82600}, {"chord": "F:maj", "start": 82600, "end": 84500}, {"chord": "G:min", "start": 84500, "end": 85000}, {"chord": "C:maj", "start": 85000, "end": 86100}, {"chord": "F:maj", "start": 86100, "end": 93900}, {"chord": "C:maj", "start": 93900, "end": 95400}, {"chord": "F:maj", "start": 95400, "end": 98600}, {"chord": "A#:maj", "start": 98600, "end": 100100}, {"chord": "F:maj", "start": 100100, "end": 101800}, {"chord": "G:min", "start": 101800, "end": 103200}, {"chord": "C:maj", "start": 103200, "end": 105000}, {"chord": "F:maj", "start": 105000, "end": 106500}, {"chord": "C:maj", "start": 106500, "end": 108100}, {"chord": "A#:maj", "start": 108100, "end": 109700}, {"chord": "F:maj", "start": 109700, "end": 111300}, {"chord": "A#:maj", "start": 111300, "end": 112800}, {"chord": "F:maj", "start": 112800, "end": 114500}, {"chord": "G:min", "start": 114500, "end": 115200}, {"chord": "C:maj", "start": 115200, "end": 116000}, {"chord": "F:maj", "start": 116000, "end": 119200}, {"chord": "C:maj", "start": 119200, "end": 120800}, {"chord": "C:min", "start": 120800, "end": 121400}, {"chord": "F:maj", "start": 121400, "end": 125500}, {"chord": "G:min", "start": 125500, "end": 128400}, {"chord": "C:maj", "start": 128400, "end": 131800}, {"chord": "A:min", "start": 131800, "end": 133400}, {"chord": "D:maj", "start": 133400, "end": 134900}, {"chord": "A#:maj", "start": 134900, "end": 136500}, {"chord": "F:maj", "start": 136500, "end": 138200}, {"chord": "A#:maj", "start": 138200, "end": 139600}, {"chord": "F:maj", "start": 139600, "end": 147600}, {"chord": "G:min", "start": 147600, "end": 148200}, {"chord": "C:maj", "start": 148200, "end": 149200}, {"chord": "F:maj", "start": 149200, "end": 152400}, {"chord": "G:min", "start": 152400, "end": 155100}, {"chord": "C:maj", "start": 155100, "end": 158100}, {"chord": "F:maj", "start": 158100, "end": 160300}, {"chord": "C:maj", "start": 160300, "end": 161700}, {"chord": "A#:maj", "start": 161700, "end": 163300}, {"chord": "F:maj", "start": 163300, "end": 165000}, {"chord": "A#:maj", "start": 165000, "end": 166500}, {"chord": "F:maj", "start": 166500, "end": 168100}, {"chord": "G:min", "start": 168100, "end": 169600}, {"chord": "C:maj", "start": 169600, "end": 171300}, {"chord": "F:maj", "start": 171300, "end": 174500}, {"chord": "A#:maj", "start": 174500, "end": 175900}, {"chord": "F:maj", "start": 175900, "end": 177600}, {"chord": "G:min", "start": 177600, "end": 179100}, {"chord": "C:maj", "start": 179100, "end": 180700}, {"chord": "F:maj", "start": 180700, "end": 183900}, {"chord": "C:maj", "start": 183900, "end": 185400}, {"chord": "C:min", "start": 185400, "end": 186200}, {"chord": "F:maj", "start": 186200, "end": 190200}, {"chord": "G:min", "start": 190200, "end": 193200}, {"chord": "C:maj", "start": 193200, "end": 196600}, {"chord": "A:min", "start": 196600, "end": 198100}, {"chord": "D:maj", "start": 198100, "end": 199400}, {"chord": "A#:maj", "start": 199400, "end": 201200}, {"chord": "F:maj", "start": 201200, "end": 203000}, {"chord": "A#:maj", "start": 203000, "end": 204300}, {"chord": "F:maj", "start": 204300, "end": 212400}, {"chord": "G:min", "start": 212400, "end": 212900}, {"chord": "C:maj", "start": 212900, "end": 214000}, {"chord": "F:maj", "start": 214000, "end": 215600}, {"chord": "A#:maj", "start": 215600, "end": 217000}, {"chord": "F:maj", "start": 217000, "end": 218700}, {"chord": "A#:maj", "start": 218700, "end": 220500}, {"chord": "F:maj", "start": 220500, "end": 221900}, {"chord": "A#:maj", "start": 221900, "end": 223400}, {"chord": "F:maj", "start": 223400, "end": 225200}, {"chord": "G:maj", "start": 225200, "end": 225900}, {"chord": "C:maj", "start": 225900, "end": 226800}, {"chord": "F:maj", "start": 226800, "end": 229900}, {"chord": "A#:maj", "start": 229900, "end": 231600}, {"chord": "F:maj", "start": 231600, "end": 233100}, {"chord": "A#:maj", "start": 233100, "end": 234700}, {"chord": "F:maj", "start": 234700, "end": 236300}, {"chord": "G:min", "start": 236300, "end": 239500}, {"chord": "C:maj", "start": 239500, "end": 244800}, {"chord": "F:maj", "start": 244800, "end": 256400}, {"chord": "N", "start": 256400, "end": 260700}]